twentykn.py
twentykn-1.0.0.dist-info/LICENSE
twentykn-1.0.0.dist-info/METADATA
twentykn-1.0.0.dist-info/WHEEL
twentykn-1.0.0.dist-info/top_level.txt
twentykn-1.0.0.dist-info/RECORD
