Metadata-Version: 2.1
Name: twentykn
Version: 1.0.0
Summary: 20KN: Twenty Kilo Numeric System (CJK-based 20,000-radix encoding)
Author: blueradiance
Author-email: noreply@example.com
License: Other/Proprietary License
Classifier: Programming Language :: Python :: 3
Classifier: License :: Other/Proprietary License
Classifier: Operating System :: OS Independent
Requires-Python: >=3.6
License-File: LICENSE
